leica_roi_finder/__init__.py
leica_roi_finder/__main__.py
leica_roi_finder/core/LIF_metadata.py
leica_roi_finder/core/__init__.py
leica_roi_finder/core/_defaults.py
leica_roi_finder/core/coords_to_xml.py
leica_roi_finder/core/roi_finder_class.py
leica_roi_finder/gui/__init__.py
leica_roi_finder/gui/gui.py
leica_roi_finder-0.0.4.dist-info/licenses/LICENSE
leica_roi_finder-0.0.4.dist-info/METADATA
leica_roi_finder-0.0.4.dist-info/WHEEL
leica_roi_finder-0.0.4.dist-info/entry_points.txt
leica_roi_finder-0.0.4.dist-info/top_level.txt
leica_roi_finder-0.0.4.dist-info/RECORD
